newgrok/__init__.py
newgrok/cli/chat.py
newgrok/modules/process_manager/manager.py
newgrok/modules/telegram/bot.py
newgrok/newgrok.py
newgrok-0.4.0.dist-info/entry_points.txt
newgrok-0.4.0.dist-info/WHEEL
newgrok-0.4.0.dist-info/METADATA
newgrok-0.4.0.dist-info/RECORD
