Metadata-Version: 2.1
Name: newgrok
Version: 0.4.0
Summary: Keep ngrok free tier alive
Author: Adrien
Author-email: adrienv.sui@gmail.com
Requires-Python: >=3.10,<4.0
Classifier: Programming Language :: Python :: 3
Classifier: Programming Language :: Python :: 3.10
Classifier: Programming Language :: Python :: 3.11
Requires-Dist: pytelegrambotapi (>=4.8.0,<5.0.0)
Requires-Dist: python-dotenv (>=0.21.0,<0.22.0)
Requires-Dist: requests (>=2.28.1,<3.0.0)
